diffweave/__init__.py
diffweave/ai.py
diffweave/cli.py
diffweave/prompt.md
diffweave/prompt_simple.md
diffweave/repo.py
diffweave/utils.py
diffweave_ai-1.1.0.dist-info/METADATA
diffweave_ai-1.1.0.dist-info/WHEEL
diffweave_ai-1.1.0.dist-info/entry_points.txt
diffweave_ai-1.1.0.dist-info/licenses/LICENSE.TXT
diffweave_ai-1.1.0.dist-info/RECORD
