Metadata-Version: 2.4
Name: diffweave-ai
Version: 1.1.0
Summary: Assists with git workflows using LLMs.
Author-email: Zoë Farmer <zfarmer@squareup.com>, Chase Hudson <chasehudson@squareup.com>
License-File: LICENSE.TXT
Requires-Python: >=3.9
Requires-Dist: beaupy>=3.10.1
Requires-Dist: cyclopts>=3.24.0
Requires-Dist: gitpython>=3.1.44
Requires-Dist: openai>=1.82.0
Requires-Dist: pyyaml>=6.0.2
